<annotationInfo>
<annotationInfo>
<item  id="99" filename="find_contours/contour_finder.cpp" linenumber="61" name="tmp_3" contextFuncName="contours_finder" moduleName="contours_finder" rtlName="tmp_3_fu_1668_p2" latency="0" BRAM="-1" DSP="-1" FF="0" LUT="32" fileDirectory="C:\Users\Lorenzo\PROGETTI_FPGA"><\/item>
<item  id="100" filename="find_contours/contour_finder.cpp" linenumber="61" name="tmp_4" contextFuncName="contours_finder" moduleName="contours_finder" rtlName="tmp_4_fu_1674_p2" latency="0" BRAM="-1" DSP="-1" FF="0" LUT="18" fileDirectory="C:\Users\Lorenzo\PROGETTI_FPGA"><\/item>
<item  id="106" filename="find_contours/contour_finder.cpp" linenumber="63" name="tmp_5" contextFuncName="contours_finder" moduleName="contours_finder" rtlName="tmp_5_fu_1680_p2" latency="0" BRAM="-1" DSP="-1" FF="0" LUT="13" fileDirectory="C:\Users\Lorenzo\PROGETTI_FPGA"><\/item>
<item  id="108" filename="find_contours/contour_finder.cpp" linenumber="63" name="count_2" contextFuncName="contours_finder" moduleName="contours_finder" rtlName="count_2_fu_1686_p2" latency="0" BRAM="-1" DSP="-1" FF="0" LUT="15" fileDirectory="C:\Users\Lorenzo\PROGETTI_FPGA"><\/item>
<item  id="111" filename="find_contours/contour_finder.cpp" linenumber="64" name="tmp_6" contextFuncName="contours_finder" moduleName="contours_finder" rtlName="tmp_6_fu_1692_p1" latency="0" BRAM="-1" DSP="-1" FF="-1" LUT="-1" fileDirectory="C:\Users\Lorenzo\PROGETTI_FPGA"><\/item>
<item  id="125" filename="find_contours/contour_finder.cpp" linenumber="75" name="tmp_8" contextFuncName="contours_finder" moduleName="contours_finder" rtlName="tmp_8_fu_1700_p2" latency="0" BRAM="-1" DSP="-1" FF="0" LUT="13" fileDirectory="C:\Users\Lorenzo\PROGETTI_FPGA"><\/item>
<item  id="127" filename="find_contours/contour_finder.cpp" linenumber="75" name="count_3" contextFuncName="contours_finder" moduleName="contours_finder" rtlName="count_3_fu_1706_p2" latency="0" BRAM="-1" DSP="-1" FF="0" LUT="14" fileDirectory="C:\Users\Lorenzo\PROGETTI_FPGA"><\/item>
<item  id="130" filename="find_contours/contour_finder.cpp" linenumber="76" name="tmp_9" contextFuncName="contours_finder" moduleName="contours_finder" rtlName="tmp_9_fu_1712_p1" latency="0" BRAM="-1" DSP="-1" FF="-1" LUT="-1" fileDirectory="C:\Users\Lorenzo\PROGETTI_FPGA"><\/item>
<item  id="145" filename="find_contours/contour_finder.cpp" linenumber="89" name="tmp_s" contextFuncName="contours_finder" moduleName="contours_finder" rtlName="tmp_s_fu_1721_p2" latency="0" BRAM="-1" DSP="-1" FF="0" LUT="18" fileDirectory="C:\Users\Lorenzo\PROGETTI_FPGA"><\/item>
<item  id="151" filename="find_contours/contour_finder.cpp" linenumber="113" name="tmp_2" contextFuncName="contours_finder" moduleName="contours_finder" rtlName="tmp_2_fu_1739_p1" latency="0" BRAM="-1" DSP="-1" FF="-1" LUT="-1" fileDirectory="C:\Users\Lorenzo\PROGETTI_FPGA"><\/item>
<item  id="154" filename="find_contours/contour_finder.cpp" linenumber="113" name="tmp" contextFuncName="contours_finder" moduleName="contours_finder" rtlName="tmp_fu_1763_p1" latency="0" BRAM="-1" DSP="-1" FF="-1" LUT="-1" fileDirectory="C:\Users\Lorenzo\PROGETTI_FPGA"><\/item>
<item  id="155" filename="find_contours/contour_finder.cpp" linenumber="113" name="tmp_20" contextFuncName="contours_finder" moduleName="contours_finder" rtlName="tmp_20_fu_1766_p1" latency="0" BRAM="-1" DSP="-1" FF="-1" LUT="-1" fileDirectory="C:\Users\Lorenzo\PROGETTI_FPGA"><\/item>
<item  id="156" filename="find_contours/contour_finder.cpp" linenumber="113" name="heigth_count_assign" contextFuncName="contours_finder" moduleName="contours_finder" rtlName="heigth_count_assign_fu_1769_p2" latency="0" BRAM="-1" DSP="-1" FF="0" LUT="23" fileDirectory="C:\Users\Lorenzo\PROGETTI_FPGA"><\/item>
<item  id="157" filename="find_contours/contour_finder.cpp" linenumber="422" name="tmp_i" contextFuncName="generateAxiValue" moduleName="contours_finder" rtlName="tmp_i_fu_1775_p2" latency="0" BRAM="-1" DSP="-1" FF="0" LUT="16" fileDirectory="C:\Users\Lorenzo\PROGETTI_FPGA"><\/item>
<item  id="158" filename="find_contours/contour_finder.cpp" linenumber="422" name="aValue_user_V_4" contextFuncName="generateAxiValue" moduleName="contours_finder" rtlName="aValue_user_V_4_fu_1781_p2" latency="0" BRAM="-1" DSP="-1" FF="0" LUT="13" fileDirectory="C:\Users\Lorenzo\PROGETTI_FPGA"><\/item>
<item  id="159" filename="find_contours/contour_finder.cpp" linenumber="427" name="aValue_last_V_2" contextFuncName="generateAxiValue" moduleName="contours_finder" rtlName="aValue_last_V_2_fu_1788_p2" latency="0" BRAM="-1" DSP="-1" FF="0" LUT="13" fileDirectory="C:\Users\Lorenzo\PROGETTI_FPGA"><\/item>
<item  id="161" filename="find_contours/contour_finder.cpp" linenumber="116" name="tmp_7" contextFuncName="contours_finder" moduleName="contours_finder" rtlName="tmp_7_fu_1756_p1" latency="0" BRAM="-1" DSP="-1" FF="-1" LUT="-1" fileDirectory="C:\Users\Lorenzo\PROGETTI_FPGA"><\/item>
<item  id="164" filename="find_contours/contour_finder.cpp" linenumber="116" name="tmp_10" contextFuncName="contours_finder" moduleName="contours_finder" rtlName="tmp_10_fu_1795_p2" latency="0" BRAM="-1" DSP="-1" FF="0" LUT="39" fileDirectory="C:\Users\Lorenzo\PROGETTI_FPGA"><\/item>
<item  id="168" filename="find_contours/contour_finder.cpp" linenumber="117" name="tmp_11" contextFuncName="contours_finder" moduleName="contours_finder" rtlName="tmp_11_fu_1802_p2" latency="0" BRAM="-1" DSP="-1" FF="0" LUT="39" fileDirectory="C:\Users\Lorenzo\PROGETTI_FPGA"><\/item>
<item  id="172" filename="find_contours/contour_finder.cpp" linenumber="118" name="tmp_12" contextFuncName="contours_finder" moduleName="contours_finder" rtlName="tmp_12_fu_1808_p2" latency="0" BRAM="-1" DSP="-1" FF="0" LUT="39" fileDirectory="C:\Users\Lorenzo\PROGETTI_FPGA"><\/item>
<item  id="174" filename="find_contours/contour_finder.cpp" linenumber="135" name="tmp_13" contextFuncName="contours_finder" moduleName="contours_finder" rtlName="grp_fu_1577_p2" latency="0" BRAM="-1" DSP="-1" FF="0" LUT="11" fileDirectory="C:\Users\Lorenzo\PROGETTI_FPGA"><\/item>
<item  id="177" filename="find_contours/contour_finder.cpp" linenumber="216" name="tmp_18" contextFuncName="contours_finder" moduleName="contours_finder" rtlName="tmp_18_fu_1814_p2" latency="0" BRAM="-1" DSP="-1" FF="0" LUT="11" fileDirectory="C:\Users\Lorenzo\PROGETTI_FPGA"><\/item>
<item  id="178" filename="find_contours/contour_finder.cpp" linenumber="216" name="tmp_19" contextFuncName="contours_finder" moduleName="contours_finder" rtlName="grp_fu_1598_p2" latency="0" BRAM="-1" DSP="-1" FF="0" LUT="11" fileDirectory="C:\Users\Lorenzo\PROGETTI_FPGA"><\/item>
<item  id="179" filename="find_contours/contour_finder.cpp" linenumber="216" name="or_cond1" contextFuncName="contours_finder" moduleName="contours_finder" rtlName="or_cond1_fu_1819_p2" latency="0" BRAM="-1" DSP="-1" FF="0" LUT="2" fileDirectory="C:\Users\Lorenzo\PROGETTI_FPGA"><\/item>
<item  id="182" filename="find_contours/contour_finder.cpp" linenumber="216" name="tmp_24" contextFuncName="contours_finder" moduleName="contours_finder" rtlName="grp_fu_1603_p2" latency="0" BRAM="-1" DSP="-1" FF="0" LUT="39" fileDirectory="C:\Users\Lorenzo\PROGETTI_FPGA"><\/item>
<item  id="183" filename="find_contours/contour_finder.cpp" linenumber="216" name="tmp_25" contextFuncName="contours_finder" moduleName="contours_finder" rtlName="tmp_25_fu_1825_p1" latency="0" BRAM="-1" DSP="-1" FF="-1" LUT="-1" fileDirectory="C:\Users\Lorenzo\PROGETTI_FPGA"><\/item>
<item  id="186" filename="find_contours/contour_finder.cpp" linenumber="216" name="tmp_26" contextFuncName="contours_finder" moduleName="contours_finder" rtlName="grp_fu_1608_p2" latency="0" BRAM="-1" DSP="-1" FF="0" LUT="11" fileDirectory="C:\Users\Lorenzo\PROGETTI_FPGA"><\/item>
<item  id="193" filename="find_contours/contour_finder.cpp" linenumber="223" name="tmp_41" contextFuncName="contours_finder" moduleName="contours_finder" rtlName="grp_fu_1582_p2" latency="0" BRAM="-1" DSP="-1" FF="0" LUT="18" fileDirectory="C:\Users\Lorenzo\PROGETTI_FPGA"><\/item>
<item  id="196" filename="find_contours/contour_finder.cpp" linenumber="224" name="tmp_46" contextFuncName="contours_finder" moduleName="contours_finder" rtlName="grp_fu_1603_p2" latency="0" BRAM="-1" DSP="-1" FF="0" LUT="39" fileDirectory="C:\Users\Lorenzo\PROGETTI_FPGA"><\/item>
<item  id="197" filename="find_contours/contour_finder.cpp" linenumber="224" name="tmp_47" contextFuncName="contours_finder" moduleName="contours_finder" rtlName="tmp_47_fu_1840_p1" latency="0" BRAM="-1" DSP="-1" FF="-1" LUT="-1" fileDirectory="C:\Users\Lorenzo\PROGETTI_FPGA"><\/item>
<item  id="200" filename="find_contours/contour_finder.cpp" linenumber="224" name="tmp_48" contextFuncName="contours_finder" moduleName="contours_finder" rtlName="tmp_48_fu_1845_p2" latency="0" BRAM="-1" DSP="-1" FF="0" LUT="11" fileDirectory="C:\Users\Lorenzo\PROGETTI_FPGA"><\/item>
<item  id="216" filename="find_contours/contour_finder.cpp" linenumber="136" name="tmp_16" contextFuncName="contours_finder" moduleName="contours_finder" rtlName="grp_fu_1598_p2" latency="0" BRAM="-1" DSP="-1" FF="0" LUT="11" fileDirectory="C:\Users\Lorenzo\PROGETTI_FPGA"><\/item>
<item  id="217" filename="find_contours/contour_finder.cpp" linenumber="201" name="tmp_17" contextFuncName="contours_finder" moduleName="contours_finder" rtlName="grp_fu_1582_p2" latency="0" BRAM="-1" DSP="-1" FF="0" LUT="18" fileDirectory="C:\Users\Lorenzo\PROGETTI_FPGA"><\/item>
<item  id="222" filename="find_contours/contour_finder.cpp" linenumber="138" name="tmp_34" contextFuncName="contours_finder" moduleName="contours_finder" rtlName="grp_fu_1603_p2" latency="0" BRAM="-1" DSP="-1" FF="0" LUT="39" fileDirectory="C:\Users\Lorenzo\PROGETTI_FPGA"><\/item>
<item  id="223" filename="find_contours/contour_finder.cpp" linenumber="138" name="tmp_35" contextFuncName="contours_finder" moduleName="contours_finder" rtlName="tmp_35_fu_1830_p1" latency="0" BRAM="-1" DSP="-1" FF="-1" LUT="-1" fileDirectory="C:\Users\Lorenzo\PROGETTI_FPGA"><\/item>
<item  id="226" filename="find_contours/contour_finder.cpp" linenumber="138" name="tmp_36" contextFuncName="contours_finder" moduleName="contours_finder" rtlName="grp_fu_1608_p2" latency="0" BRAM="-1" DSP="-1" FF="0" LUT="11" fileDirectory="C:\Users\Lorenzo\PROGETTI_FPGA"><\/item>
<item  id="227" filename="find_contours/contour_finder.cpp" linenumber="138" name="tmp_37" contextFuncName="contours_finder" moduleName="contours_finder" rtlName="grp_fu_1650_p2" latency="0" BRAM="-1" DSP="-1" FF="0" LUT="11" fileDirectory="C:\Users\Lorenzo\PROGETTI_FPGA"><\/item>
<item  id="228" filename="find_contours/contour_finder.cpp" linenumber="138" name="or_cond" contextFuncName="contours_finder" moduleName="contours_finder" rtlName="or_cond_fu_1851_p2" latency="0" BRAM="-1" DSP="-1" FF="0" LUT="2" fileDirectory="C:\Users\Lorenzo\PROGETTI_FPGA"><\/item>
<item  id="231" filename="find_contours/contour_finder.cpp" linenumber="139" name="tmp_40" contextFuncName="contours_finder" moduleName="contours_finder" rtlName="tmp_40_fu_1857_p2" latency="0" BRAM="-1" DSP="-1" FF="0" LUT="11" fileDirectory="C:\Users\Lorenzo\PROGETTI_FPGA"><\/item>
<item  id="234" filename="find_contours/contour_finder.cpp" linenumber="422" name="tmp_i1" contextFuncName="generateAxiValue" moduleName="contours_finder" rtlName="tmp_i1_fu_1883_p2" latency="0" BRAM="-1" DSP="-1" FF="0" LUT="16" fileDirectory="C:\Users\Lorenzo\PROGETTI_FPGA"><\/item>
<item  id="235" filename="find_contours/contour_finder.cpp" linenumber="422" name="aValue_user_V" contextFuncName="generateAxiValue" moduleName="contours_finder" rtlName="aValue_user_V_fu_1887_p2" latency="0" BRAM="-1" DSP="-1" FF="0" LUT="13" fileDirectory="C:\Users\Lorenzo\PROGETTI_FPGA"><\/item>
<item  id="238" filename="find_contours/contour_finder.cpp" linenumber="168" name="tmp_42" contextFuncName="contours_finder" moduleName="contours_finder" rtlName="tmp_42_fu_1862_p1" latency="0" BRAM="-1" DSP="-1" FF="-1" LUT="-1" fileDirectory="C:\Users\Lorenzo\PROGETTI_FPGA"><\/item>
<item  id="241" filename="find_contours/contour_finder.cpp" linenumber="168" name="tmp_43" contextFuncName="contours_finder" moduleName="contours_finder" rtlName="tmp_43_fu_1868_p2" latency="0" BRAM="-1" DSP="-1" FF="0" LUT="39" fileDirectory="C:\Users\Lorenzo\PROGETTI_FPGA"><\/item>
<item  id="246" filename="find_contours/contour_finder.cpp" linenumber="170" name="tmp_44" contextFuncName="contours_finder" moduleName="contours_finder" rtlName="tmp_44_fu_1873_p2" latency="0" BRAM="-1" DSP="-1" FF="0" LUT="39" fileDirectory="C:\Users\Lorenzo\PROGETTI_FPGA"><\/item>
<item  id="251" filename="find_contours/contour_finder.cpp" linenumber="172" name="tmp_45" contextFuncName="contours_finder" moduleName="contours_finder" rtlName="tmp_45_fu_1878_p2" latency="0" BRAM="-1" DSP="-1" FF="0" LUT="39" fileDirectory="C:\Users\Lorenzo\PROGETTI_FPGA"><\/item>
<item  id="257" filename="find_contours/contour_finder.cpp" linenumber="180" name="exitcond1" contextFuncName="contours_finder" moduleName="contours_finder" rtlName="exitcond1_fu_1895_p2" latency="0" BRAM="-1" DSP="-1" FF="0" LUT="13" fileDirectory="C:\Users\Lorenzo\PROGETTI_FPGA"><\/item>
<item  id="259" filename="find_contours/contour_finder.cpp" linenumber="180" name="count_5" contextFuncName="contours_finder" moduleName="contours_finder" rtlName="count_5_fu_1901_p2" latency="0" BRAM="-1" DSP="-1" FF="0" LUT="14" fileDirectory="C:\Users\Lorenzo\PROGETTI_FPGA"><\/item>
<item  id="262" filename="find_contours/contour_finder.cpp" linenumber="181" name="tmp_49" contextFuncName="contours_finder" moduleName="contours_finder" rtlName="tmp_49_fu_1907_p1" latency="0" BRAM="-1" DSP="-1" FF="-1" LUT="-1" fileDirectory="C:\Users\Lorenzo\PROGETTI_FPGA"><\/item>
<item  id="265" filename="find_contours/contour_finder.cpp" linenumber="181" name="tmp_50" contextFuncName="contours_finder" moduleName="contours_finder" rtlName="tmp_50_fu_1912_p2" latency="0" BRAM="-1" DSP="-1" FF="0" LUT="11" fileDirectory="C:\Users\Lorenzo\PROGETTI_FPGA"><\/item>
<item  id="273" filename="find_contours/contour_finder.cpp" linenumber="184" name="tmp_51" contextFuncName="contours_finder" moduleName="contours_finder" rtlName="tmp_51_fu_1917_p2" latency="0" BRAM="-1" DSP="-1" FF="0" LUT="11" fileDirectory="C:\Users\Lorenzo\PROGETTI_FPGA"><\/item>
<item  id="288" filename="find_contours/contour_finder.cpp" linenumber="194" name="tmp_52" contextFuncName="contours_finder" moduleName="contours_finder" rtlName="tmp_52_fu_1922_p1" latency="0" BRAM="-1" DSP="-1" FF="-1" LUT="-1" fileDirectory="C:\Users\Lorenzo\PROGETTI_FPGA"><\/item>
<item  id="291" filename="find_contours/contour_finder.cpp" linenumber="194" name="tmp_53" contextFuncName="contours_finder" moduleName="contours_finder" rtlName="grp_fu_1608_p2" latency="0" BRAM="-1" DSP="-1" FF="0" LUT="11" fileDirectory="C:\Users\Lorenzo\PROGETTI_FPGA"><\/item>
<item  id="296" filename="find_contours/contour_finder.cpp" linenumber="196" name="count_6" contextFuncName="contours_finder" moduleName="contours_finder" rtlName="count_6_fu_1927_p2" latency="0" BRAM="-1" DSP="-1" FF="0" LUT="39" fileDirectory="C:\Users\Lorenzo\PROGETTI_FPGA"><\/item>
<item  id="299" filename="find_contours/contour_finder.cpp" linenumber="198" name="tmp_54" contextFuncName="contours_finder" moduleName="contours_finder" rtlName="tmp_54_fu_1933_p2" latency="0" BRAM="-1" DSP="-1" FF="0" LUT="23" fileDirectory="C:\Users\Lorenzo\PROGETTI_FPGA"><\/item>
<item  id="305" filename="find_contours/contour_finder.cpp" linenumber="201" name="tmp_31" contextFuncName="contours_finder" moduleName="contours_finder" rtlName="grp_fu_1603_p2" latency="0" BRAM="-1" DSP="-1" FF="0" LUT="39" fileDirectory="C:\Users\Lorenzo\PROGETTI_FPGA"><\/item>
<item  id="306" filename="find_contours/contour_finder.cpp" linenumber="201" name="tmp_32" contextFuncName="contours_finder" moduleName="contours_finder" rtlName="tmp_32_fu_1835_p1" latency="0" BRAM="-1" DSP="-1" FF="-1" LUT="-1" fileDirectory="C:\Users\Lorenzo\PROGETTI_FPGA"><\/item>
<item  id="309" filename="find_contours/contour_finder.cpp" linenumber="201" name="tmp_33" contextFuncName="contours_finder" moduleName="contours_finder" rtlName="grp_fu_1608_p2" latency="0" BRAM="-1" DSP="-1" FF="0" LUT="11" fileDirectory="C:\Users\Lorenzo\PROGETTI_FPGA"><\/item>
<item  id="315" filename="find_contours/contour_finder.cpp" linenumber="206" name="tmp_57" contextFuncName="contours_finder" moduleName="contours_finder" rtlName="tmp_57_fu_1970_p1" latency="0" BRAM="-1" DSP="-1" FF="-1" LUT="-1" fileDirectory="C:\Users\Lorenzo\PROGETTI_FPGA"><\/item>
<item  id="317" filename="find_contours/contour_finder.cpp" linenumber="207" name="tmp_39" contextFuncName="contours_finder" moduleName="contours_finder" rtlName="grp_fu_1587_p2" latency="0" BRAM="-1" DSP="-1" FF="0" LUT="23" fileDirectory="C:\Users\Lorenzo\PROGETTI_FPGA"><\/item>
<item  id="327" filename="find_contours/contour_finder.cpp" linenumber="422" name="tmp_i2" contextFuncName="generateAxiValue" moduleName="contours_finder" rtlName="tmp_i2_fu_1944_p2" latency="0" BRAM="-1" DSP="-1" FF="0" LUT="16" fileDirectory="C:\Users\Lorenzo\PROGETTI_FPGA"><\/item>
<item  id="328" filename="find_contours/contour_finder.cpp" linenumber="422" name="aValue_user_V_5" contextFuncName="generateAxiValue" moduleName="contours_finder" rtlName="aValue_user_V_5_fu_1948_p2" latency="0" BRAM="-1" DSP="-1" FF="0" LUT="13" fileDirectory="C:\Users\Lorenzo\PROGETTI_FPGA"><\/item>
<item  id="333" filename="find_contours/contour_finder.cpp" linenumber="90" name="tmp_1" contextFuncName="contours_finder" moduleName="contours_finder" rtlName="grp_fu_1577_p2" latency="0" BRAM="-1" DSP="-1" FF="0" LUT="11" fileDirectory="C:\Users\Lorenzo\PROGETTI_FPGA"><\/item>
<item  id="336" filename="find_contours/contour_finder.cpp" linenumber="103" name="tmp_15" contextFuncName="contours_finder" moduleName="contours_finder" rtlName="tmp_15_fu_1743_p1" latency="0" BRAM="-1" DSP="-1" FF="-1" LUT="-1" fileDirectory="C:\Users\Lorenzo\PROGETTI_FPGA"><\/item>
<item  id="341" filename="find_contours/contour_finder.cpp" linenumber="91" name="tmp_14" contextFuncName="contours_finder" moduleName="contours_finder" rtlName="grp_fu_1582_p2" latency="0" BRAM="-1" DSP="-1" FF="0" LUT="18" fileDirectory="C:\Users\Lorenzo\PROGETTI_FPGA"><\/item>
<item  id="344" filename="find_contours/contour_finder.cpp" linenumber="92" name="tmp_22" contextFuncName="contours_finder" moduleName="contours_finder" rtlName="tmp_22_fu_1747_p1" latency="0" BRAM="-1" DSP="-1" FF="-1" LUT="-1" fileDirectory="C:\Users\Lorenzo\PROGETTI_FPGA"><\/item>
<item  id="347" filename="find_contours/contour_finder.cpp" linenumber="92" name="tmp_23" contextFuncName="contours_finder" moduleName="contours_finder" rtlName="grp_fu_1608_p2" latency="0" BRAM="-1" DSP="-1" FF="0" LUT="11" fileDirectory="C:\Users\Lorenzo\PROGETTI_FPGA"><\/item>
<item  id="350" filename="find_contours/contour_finder.cpp" linenumber="93" name="tmp_29" contextFuncName="contours_finder" moduleName="contours_finder" rtlName="grp_fu_1603_p2" latency="0" BRAM="-1" DSP="-1" FF="0" LUT="39" fileDirectory="C:\Users\Lorenzo\PROGETTI_FPGA"><\/item>
<item  id="351" filename="find_contours/contour_finder.cpp" linenumber="93" name="tmp_30" contextFuncName="contours_finder" moduleName="contours_finder" rtlName="tmp_30_fu_1974_p1" latency="0" BRAM="-1" DSP="-1" FF="-1" LUT="-1" fileDirectory="C:\Users\Lorenzo\PROGETTI_FPGA"><\/item>
<item  id="357" filename="find_contours/contour_finder.cpp" linenumber="95" name="tmp_38" contextFuncName="contours_finder" moduleName="contours_finder" rtlName="tmp_38_fu_1979_p1" latency="0" BRAM="-1" DSP="-1" FF="-1" LUT="-1" fileDirectory="C:\Users\Lorenzo\PROGETTI_FPGA"><\/item>
<item  id="359" filename="find_contours/contour_finder.cpp" linenumber="96" name="tmp_28" contextFuncName="contours_finder" moduleName="contours_finder" rtlName="grp_fu_1587_p2" latency="0" BRAM="-1" DSP="-1" FF="0" LUT="23" fileDirectory="C:\Users\Lorenzo\PROGETTI_FPGA"><\/item>
<item  id="365" filename="find_contours/contour_finder.cpp" linenumber="99" name="tmp_27" contextFuncName="contours_finder" moduleName="contours_finder" rtlName="tmp_27_fu_1751_p1" latency="0" BRAM="-1" DSP="-1" FF="-1" LUT="-1" fileDirectory="C:\Users\Lorenzo\PROGETTI_FPGA"><\/item>
<item  id="367" filename="find_contours/contour_finder.cpp" linenumber="100" name="tmp_21" contextFuncName="contours_finder" moduleName="contours_finder" rtlName="grp_fu_1587_p2" latency="0" BRAM="-1" DSP="-1" FF="0" LUT="23" fileDirectory="C:\Users\Lorenzo\PROGETTI_FPGA"><\/item>
<item  id="373" filename="find_contours/contour_finder.cpp" linenumber="105" name="tmp_58" contextFuncName="contours_finder" moduleName="contours_finder" rtlName="tmp_58_fu_1983_p1" latency="0" BRAM="-1" DSP="-1" FF="-1" LUT="-1" fileDirectory="C:\Users\Lorenzo\PROGETTI_FPGA"><\/item>
<item  id="374" filename="find_contours/contour_finder.cpp" linenumber="422" name="aValue_user_V_3" contextFuncName="generateAxiValue" moduleName="contours_finder" rtlName="aValue_user_V_3_fu_1986_p2" latency="0" BRAM="-1" DSP="-1" FF="0" LUT="13" fileDirectory="C:\Users\Lorenzo\PROGETTI_FPGA"><\/item>
<item  id="375" filename="find_contours/contour_finder.cpp" linenumber="427" name="aValue_last_V" contextFuncName="generateAxiValue" moduleName="contours_finder" rtlName="aValue_last_V_fu_1994_p2" latency="0" BRAM="-1" DSP="-1" FF="0" LUT="13" fileDirectory="C:\Users\Lorenzo\PROGETTI_FPGA"><\/item>
<item  id="384" filename="find_contours/contour_finder.cpp" linenumber="253" name="tmp_55" contextFuncName="contours_finder" moduleName="contours_finder" rtlName="tmp_55_fu_1956_p2" latency="0" BRAM="-1" DSP="-1" FF="0" LUT="39" fileDirectory="C:\Users\Lorenzo\PROGETTI_FPGA"><\/item>
<item  id="385" filename="find_contours/contour_finder.cpp" linenumber="254" name="tmp_56" contextFuncName="contours_finder" moduleName="contours_finder" rtlName="tmp_56_fu_1961_p2" latency="0" BRAM="-1" DSP="-1" FF="0" LUT="18" fileDirectory="C:\Users\Lorenzo\PROGETTI_FPGA"><\/item>
<item  id="388" filename="find_contours/contour_finder.cpp" linenumber="272" name="tmp_62" contextFuncName="contours_finder" moduleName="contours_finder" rtlName="tmp_62_fu_1967_p1" latency="0" BRAM="-1" DSP="-1" FF="-1" LUT="-1" fileDirectory="C:\Users\Lorenzo\PROGETTI_FPGA"><\/item>
<item  id="392" filename="find_contours/contour_finder.cpp" linenumber="259" name="tmp_96" contextFuncName="contours_finder" moduleName="contours_finder" rtlName="tmp_96_fu_2002_p4" latency="0" BRAM="-1" DSP="-1" FF="-1" LUT="-1" fileDirectory="C:\Users\Lorenzo\PROGETTI_FPGA"><\/item>
<item  id="393" filename="find_contours/contour_finder.cpp" linenumber="259" name="icmp" contextFuncName="contours_finder" moduleName="contours_finder" rtlName="icmp_fu_2012_p2" latency="0" BRAM="-1" DSP="-1" FF="0" LUT="18" fileDirectory="C:\Users\Lorenzo\PROGETTI_FPGA"><\/item>
<item  id="396" filename="find_contours/contour_finder.cpp" linenumber="261" name="tmp_59" contextFuncName="contours_finder" moduleName="contours_finder" rtlName="tmp_59_fu_2018_p1" latency="0" BRAM="-1" DSP="-1" FF="-1" LUT="-1" fileDirectory="C:\Users\Lorenzo\PROGETTI_FPGA"><\/item>
<item  id="399" filename="find_contours/contour_finder.cpp" linenumber="261" name="tmp_60" contextFuncName="contours_finder" moduleName="contours_finder" rtlName="tmp_60_fu_2023_p2" latency="0" BRAM="-1" DSP="-1" FF="0" LUT="11" fileDirectory="C:\Users\Lorenzo\PROGETTI_FPGA"><\/item>
<item  id="405" filename="find_contours/contour_finder.cpp" linenumber="264" name="tmp_61" contextFuncName="contours_finder" moduleName="contours_finder" rtlName="tmp_61_fu_2029_p1" latency="0" BRAM="-1" DSP="-1" FF="-1" LUT="-1" fileDirectory="C:\Users\Lorenzo\PROGETTI_FPGA"><\/item>
<item  id="408" filename="find_contours/contour_finder.cpp" linenumber="264" name="tmp_102" contextFuncName="contours_finder" moduleName="contours_finder" rtlName="tmp_102_fu_2034_p4" latency="0" BRAM="-1" DSP="-1" FF="-1" LUT="-1" fileDirectory="C:\Users\Lorenzo\PROGETTI_FPGA"><\/item>
<item  id="409" filename="find_contours/contour_finder.cpp" linenumber="264" name="icmp1" contextFuncName="contours_finder" moduleName="contours_finder" rtlName="icmp1_fu_2044_p2" latency="0" BRAM="-1" DSP="-1" FF="0" LUT="18" fileDirectory="C:\Users\Lorenzo\PROGETTI_FPGA"><\/item>
<item  id="410" filename="find_contours/contour_finder.cpp" linenumber="264" name="not_s" contextFuncName="contours_finder" moduleName="contours_finder" rtlName="not_s_fu_2050_p2" latency="0" BRAM="-1" DSP="-1" FF="0" LUT="11" fileDirectory="C:\Users\Lorenzo\PROGETTI_FPGA"><\/item>
<item  id="411" filename="find_contours/contour_finder.cpp" linenumber="264" name="p_s" contextFuncName="contours_finder" moduleName="contours_finder" rtlName="p_s_fu_2056_p2" latency="0" BRAM="-1" DSP="-1" FF="0" LUT="2" fileDirectory="C:\Users\Lorenzo\PROGETTI_FPGA"><\/item>
<item  id="414" filename="find_contours/contour_finder.cpp" linenumber="265" name="count_for_new_holes_1" contextFuncName="contours_finder" moduleName="contours_finder" rtlName="count_for_new_holes_1_fu_2061_p2" latency="0" BRAM="-1" DSP="-1" FF="0" LUT="39" fileDirectory="C:\Users\Lorenzo\PROGETTI_FPGA"><\/item>
<item  id="417" filename="find_contours/contour_finder.cpp" linenumber="267" name="tmp_66" contextFuncName="contours_finder" moduleName="contours_finder" rtlName="tmp_66_fu_2067_p2" latency="0" BRAM="-1" DSP="-1" FF="0" LUT="18" fileDirectory="C:\Users\Lorenzo\PROGETTI_FPGA"><\/item>
<item  id="422" filename="find_contours/contour_finder.cpp" linenumber="268" name="tmp_69" contextFuncName="contours_finder" moduleName="contours_finder" rtlName="tmp_69_fu_2073_p2" latency="0" BRAM="-1" DSP="-1" FF="0" LUT="11" fileDirectory="C:\Users\Lorenzo\PROGETTI_FPGA"><\/item>
<item  id="428" filename="find_contours/contour_finder.cpp" linenumber="270" name="tmp_70" contextFuncName="contours_finder" moduleName="contours_finder" rtlName="tmp_70_fu_2078_p2" latency="0" BRAM="-1" DSP="-1" FF="0" LUT="18" fileDirectory="C:\Users\Lorenzo\PROGETTI_FPGA"><\/item>
<item  id="431" filename="find_contours/contour_finder.cpp" linenumber="271" name="tmp_71" contextFuncName="contours_finder" moduleName="contours_finder" rtlName="tmp_71_fu_2084_p1" latency="0" BRAM="-1" DSP="-1" FF="-1" LUT="-1" fileDirectory="C:\Users\Lorenzo\PROGETTI_FPGA"><\/item>
<item  id="436" filename="find_contours/contour_finder.cpp" linenumber="270" name="count_for_copy_1" contextFuncName="contours_finder" moduleName="contours_finder" rtlName="count_for_copy_1_fu_2090_p2" latency="0" BRAM="-1" DSP="-1" FF="0" LUT="39" fileDirectory="C:\Users\Lorenzo\PROGETTI_FPGA"><\/item>
<item  id="442" filename="find_contours/contour_finder.cpp" linenumber="279" name="tmp_73" contextFuncName="contours_finder" moduleName="contours_finder" rtlName="tmp_73_fu_2096_p1" latency="0" BRAM="-1" DSP="-1" FF="-1" LUT="-1" fileDirectory="C:\Users\Lorenzo\PROGETTI_FPGA"><\/item>
<item  id="445" filename="find_contours/contour_finder.cpp" linenumber="279" name="tmp_74" contextFuncName="contours_finder" moduleName="contours_finder" rtlName="grp_fu_1614_p2" latency="0" BRAM="-1" DSP="-1" FF="0" LUT="11" fileDirectory="C:\Users\Lorenzo\PROGETTI_FPGA"><\/item>
<item  id="452" filename="find_contours/contour_finder.cpp" linenumber="286" name="tmp_81" contextFuncName="contours_finder" moduleName="contours_finder" rtlName="tmp_81_fu_2101_p1" latency="0" BRAM="-1" DSP="-1" FF="-1" LUT="-1" fileDirectory="C:\Users\Lorenzo\PROGETTI_FPGA"><\/item>
<item  id="455" filename="find_contours/contour_finder.cpp" linenumber="286" name="tmp_82" contextFuncName="contours_finder" moduleName="contours_finder" rtlName="grp_fu_1614_p2" latency="0" BRAM="-1" DSP="-1" FF="0" LUT="11" fileDirectory="C:\Users\Lorenzo\PROGETTI_FPGA"><\/item>
<item  id="460" filename="find_contours/contour_finder.cpp" linenumber="287" name="tmp_85" contextFuncName="contours_finder" moduleName="contours_finder" rtlName="tmp_85_fu_2117_p2" latency="0" BRAM="-1" DSP="-1" FF="0" LUT="11" fileDirectory="C:\Users\Lorenzo\PROGETTI_FPGA"><\/item>
<item  id="461" filename="find_contours/contour_finder.cpp" linenumber="287" name="correctly_closed_hol_1" contextFuncName="contours_finder" moduleName="contours_finder" rtlName="correctly_closed_hol_1_fu_2122_p2" latency="0" BRAM="-1" DSP="-1" FF="0" LUT="2" fileDirectory="C:\Users\Lorenzo\PROGETTI_FPGA"><\/item>
<item  id="462" filename="find_contours/contour_finder.cpp" linenumber="290" name="count_closing_2" contextFuncName="contours_finder" moduleName="contours_finder" rtlName="count_closing_2_fu_2106_p2" latency="0" BRAM="-1" DSP="-1" FF="0" LUT="39" fileDirectory="C:\Users\Lorenzo\PROGETTI_FPGA"><\/item>
<item  id="470" filename="find_contours/contour_finder.cpp" linenumber="318" name="tmp_92" contextFuncName="contours_finder" moduleName="contours_finder" rtlName="tmp_92_fu_2128_p1" latency="0" BRAM="-1" DSP="-1" FF="-1" LUT="-1" fileDirectory="C:\Users\Lorenzo\PROGETTI_FPGA"><\/item>
<item  id="473" filename="find_contours/contour_finder.cpp" linenumber="318" name="tmp_93" contextFuncName="contours_finder" moduleName="contours_finder" rtlName="grp_fu_1608_p2" latency="0" BRAM="-1" DSP="-1" FF="0" LUT="11" fileDirectory="C:\Users\Lorenzo\PROGETTI_FPGA"><\/item>
<item  id="474" filename="find_contours/contour_finder.cpp" linenumber="318" name="tmp_94" contextFuncName="contours_finder" moduleName="contours_finder" rtlName="tmp_94_fu_2133_p2" latency="0" BRAM="-1" DSP="-1" FF="0" LUT="18" fileDirectory="C:\Users\Lorenzo\PROGETTI_FPGA"><\/item>
<item  id="475" filename="find_contours/contour_finder.cpp" linenumber="318" name="p_2" contextFuncName="contours_finder" moduleName="contours_finder" rtlName="p_2_fu_2139_p2" latency="0" BRAM="-1" DSP="-1" FF="0" LUT="2" fileDirectory="C:\Users\Lorenzo\PROGETTI_FPGA"><\/item>
<item  id="481" filename="find_contours/contour_finder.cpp" linenumber="320" name="count_enlarge_right" contextFuncName="contours_finder" moduleName="contours_finder" rtlName="count_enlarge_right_fu_2145_p2" latency="0" BRAM="-1" DSP="-1" FF="0" LUT="39" fileDirectory="C:\Users\Lorenzo\PROGETTI_FPGA"><\/item>
<item  id="487" filename="find_contours/contour_finder.cpp" linenumber="322" name="tmp_97" contextFuncName="contours_finder" moduleName="contours_finder" rtlName="tmp_97_fu_2151_p1" latency="0" BRAM="-1" DSP="-1" FF="-1" LUT="-1" fileDirectory="C:\Users\Lorenzo\PROGETTI_FPGA"><\/item>
<item  id="490" filename="find_contours/contour_finder.cpp" linenumber="322" name="tmp_98" contextFuncName="contours_finder" moduleName="contours_finder" rtlName="grp_fu_1608_p2" latency="0" BRAM="-1" DSP="-1" FF="0" LUT="11" fileDirectory="C:\Users\Lorenzo\PROGETTI_FPGA"><\/item>
<item  id="491" filename="find_contours/contour_finder.cpp" linenumber="322" name="tmp_99" contextFuncName="contours_finder" moduleName="contours_finder" rtlName="tmp_99_fu_2156_p2" latency="0" BRAM="-1" DSP="-1" FF="0" LUT="18" fileDirectory="C:\Users\Lorenzo\PROGETTI_FPGA"><\/item>
<item  id="492" filename="find_contours/contour_finder.cpp" linenumber="322" name="p_4" contextFuncName="contours_finder" moduleName="contours_finder" rtlName="p_4_fu_2162_p2" latency="0" BRAM="-1" DSP="-1" FF="0" LUT="2" fileDirectory="C:\Users\Lorenzo\PROGETTI_FPGA"><\/item>
<item  id="498" filename="find_contours/contour_finder.cpp" linenumber="324" name="count_enlarge_left" contextFuncName="contours_finder" moduleName="contours_finder" rtlName="count_enlarge_left_fu_2168_p2" latency="0" BRAM="-1" DSP="-1" FF="0" LUT="39" fileDirectory="C:\Users\Lorenzo\PROGETTI_FPGA"><\/item>
<item  id="502" filename="find_contours/contour_finder.cpp" linenumber="329" name="tmp_100" contextFuncName="contours_finder" moduleName="contours_finder" rtlName="tmp_100_fu_2174_p2" latency="0" BRAM="-1" DSP="-1" FF="0" LUT="11" fileDirectory="C:\Users\Lorenzo\PROGETTI_FPGA"><\/item>
<item  id="503" filename="find_contours/contour_finder.cpp" linenumber="329" name="tmp_101" contextFuncName="contours_finder" moduleName="contours_finder" rtlName="grp_fu_1650_p2" latency="0" BRAM="-1" DSP="-1" FF="0" LUT="11" fileDirectory="C:\Users\Lorenzo\PROGETTI_FPGA"><\/item>
<item  id="504" filename="find_contours/contour_finder.cpp" linenumber="329" name="or_cond2" contextFuncName="contours_finder" moduleName="contours_finder" rtlName="or_cond2_fu_2180_p2" latency="0" BRAM="-1" DSP="-1" FF="0" LUT="2" fileDirectory="C:\Users\Lorenzo\PROGETTI_FPGA"><\/item>
<item  id="510" filename="find_contours/contour_finder.cpp" linenumber="333" name="tmp_105" contextFuncName="contours_finder" moduleName="contours_finder" rtlName="tmp_105_fu_2193_p2" latency="0" BRAM="-1" DSP="-1" FF="0" LUT="18" fileDirectory="C:\Users\Lorenzo\PROGETTI_FPGA"><\/item>
<item  id="513" filename="find_contours/contour_finder.cpp" linenumber="334" name="tmp_109" contextFuncName="contours_finder" moduleName="contours_finder" rtlName="tmp_109_fu_2199_p1" latency="0" BRAM="-1" DSP="-1" FF="-1" LUT="-1" fileDirectory="C:\Users\Lorenzo\PROGETTI_FPGA"><\/item>
<item  id="516" filename="find_contours/contour_finder.cpp" linenumber="333" name="count_delete" contextFuncName="contours_finder" moduleName="contours_finder" rtlName="count_delete_fu_2204_p2" latency="0" BRAM="-1" DSP="-1" FF="0" LUT="39" fileDirectory="C:\Users\Lorenzo\PROGETTI_FPGA"><\/item>
<item  id="521" filename="find_contours/contour_finder.cpp" linenumber="342" name="tmp_116" contextFuncName="contours_finder" moduleName="contours_finder" rtlName="tmp_116_fu_2185_p1" latency="0" BRAM="-1" DSP="-1" FF="-1" LUT="-1" fileDirectory="C:\Users\Lorenzo\PROGETTI_FPGA"><\/item>
<item  id="522" filename="find_contours/contour_finder.cpp" linenumber="345" name="tmp_117" contextFuncName="contours_finder" moduleName="contours_finder" rtlName="tmp_117_fu_2189_p1" latency="0" BRAM="-1" DSP="-1" FF="-1" LUT="-1" fileDirectory="C:\Users\Lorenzo\PROGETTI_FPGA"><\/item>
<item  id="527" filename="find_contours/contour_finder.cpp" linenumber="340" name="tmp_104" contextFuncName="contours_finder" moduleName="contours_finder" rtlName="tmp_104_fu_2210_p2" latency="0" BRAM="-1" DSP="-1" FF="0" LUT="18" fileDirectory="C:\Users\Lorenzo\PROGETTI_FPGA"><\/item>
<item  id="530" filename="find_contours/contour_finder.cpp" linenumber="341" name="tmp_106" contextFuncName="contours_finder" moduleName="contours_finder" rtlName="tmp_106_fu_2216_p1" latency="0" BRAM="-1" DSP="-1" FF="-1" LUT="-1" fileDirectory="C:\Users\Lorenzo\PROGETTI_FPGA"><\/item>
<item  id="533" filename="find_contours/contour_finder.cpp" linenumber="341" name="tmp_107" contextFuncName="contours_finder" moduleName="contours_finder" rtlName="tmp_107_fu_2221_p1" latency="0" BRAM="-1" DSP="-1" FF="-1" LUT="-1" fileDirectory="C:\Users\Lorenzo\PROGETTI_FPGA"><\/item>
<item  id="534" filename="find_contours/contour_finder.cpp" linenumber="341" name="tmp_108" contextFuncName="contours_finder" moduleName="contours_finder" rtlName="tmp_108_fu_2225_p2" latency="0" BRAM="-1" DSP="-1" FF="0" LUT="18" fileDirectory="C:\Users\Lorenzo\PROGETTI_FPGA"><\/item>
<item  id="542" filename="find_contours/contour_finder.cpp" linenumber="344" name="tmp_110" contextFuncName="contours_finder" moduleName="contours_finder" rtlName="tmp_110_fu_2231_p1" latency="0" BRAM="-1" DSP="-1" FF="-1" LUT="-1" fileDirectory="C:\Users\Lorenzo\PROGETTI_FPGA"><\/item>
<item  id="543" filename="find_contours/contour_finder.cpp" linenumber="344" name="tmp_111" contextFuncName="contours_finder" moduleName="contours_finder" rtlName="tmp_111_fu_2235_p2" latency="0" BRAM="-1" DSP="-1" FF="0" LUT="18" fileDirectory="C:\Users\Lorenzo\PROGETTI_FPGA"><\/item>
<item  id="554" filename="find_contours/contour_finder.cpp" linenumber="340" name="reshape_metadata_1" contextFuncName="contours_finder" moduleName="contours_finder" rtlName="reshape_metadata_1_fu_2241_p2" latency="0" BRAM="-1" DSP="-1" FF="0" LUT="39" fileDirectory="C:\Users\Lorenzo\PROGETTI_FPGA"><\/item>
<item  id="562" filename="find_contours/contour_finder.cpp" linenumber="353" name="tmp_112" contextFuncName="contours_finder" moduleName="contours_finder" rtlName="tmp_112_fu_2247_p1" latency="0" BRAM="-1" DSP="-1" FF="-1" LUT="-1" fileDirectory="C:\Users\Lorenzo\PROGETTI_FPGA"><\/item>
<item  id="565" filename="find_contours/contour_finder.cpp" linenumber="353" name="tmp_113" contextFuncName="contours_finder" moduleName="contours_finder" rtlName="grp_fu_1614_p2" latency="0" BRAM="-1" DSP="-1" FF="0" LUT="11" fileDirectory="C:\Users\Lorenzo\PROGETTI_FPGA"><\/item>
<item  id="570" filename="find_contours/contour_finder.cpp" linenumber="354" name="tmp_114" contextFuncName="contours_finder" moduleName="contours_finder" rtlName="grp_fu_1608_p2" latency="0" BRAM="-1" DSP="-1" FF="0" LUT="11" fileDirectory="C:\Users\Lorenzo\PROGETTI_FPGA"><\/item>
<item  id="574" filename="find_contours/contour_finder.cpp" linenumber="354" name="tmp_115" contextFuncName="contours_finder" moduleName="contours_finder" rtlName="tmp_115_fu_2252_p2" latency="0" BRAM="-1" DSP="-1" FF="0" LUT="11" fileDirectory="C:\Users\Lorenzo\PROGETTI_FPGA"><\/item>
<item  id="586" filename="find_contours/contour_finder.cpp" linenumber="361" name="count_shrink_1" contextFuncName="contours_finder" moduleName="contours_finder" rtlName="count_shrink_1_fu_2258_p2" latency="0" BRAM="-1" DSP="-1" FF="0" LUT="39" fileDirectory="C:\Users\Lorenzo\PROGETTI_FPGA"><\/item>
<item  id="591" filename="find_contours/contour_finder.cpp" linenumber="293" name="tmp_88" contextFuncName="contours_finder" moduleName="contours_finder" rtlName="tmp_88_fu_2112_p1" latency="0" BRAM="-1" DSP="-1" FF="-1" LUT="-1" fileDirectory="C:\Users\Lorenzo\PROGETTI_FPGA"><\/item>
<item  id="594" filename="find_contours/contour_finder.cpp" linenumber="293" name="tmp_89" contextFuncName="contours_finder" moduleName="contours_finder" rtlName="tmp_89_fu_2264_p2" latency="0" BRAM="-1" DSP="-1" FF="0" LUT="13" fileDirectory="C:\Users\Lorenzo\PROGETTI_FPGA"><\/item>
<item  id="599" filename="find_contours/contour_finder.cpp" linenumber="294" name="tmp_108_cast" contextFuncName="contours_finder" moduleName="contours_finder" rtlName="tmp_108_cast_fu_2270_p1" latency="0" BRAM="-1" DSP="-1" FF="-1" LUT="-1" fileDirectory="C:\Users\Lorenzo\PROGETTI_FPGA"><\/item>
<item  id="602" filename="find_contours/contour_finder.cpp" linenumber="294" name="tmp_109_cast" contextFuncName="contours_finder" moduleName="contours_finder" rtlName="tmp_109_cast_fu_2273_p1" latency="0" BRAM="-1" DSP="-1" FF="-1" LUT="-1" fileDirectory="C:\Users\Lorenzo\PROGETTI_FPGA"><\/item>
<item  id="603" filename="find_contours/contour_finder.cpp" linenumber="294" name="tmp_90" contextFuncName="contours_finder" moduleName="contours_finder" rtlName="tmp_90_fu_2277_p2" latency="0" BRAM="-1" DSP="-1" FF="0" LUT="24" fileDirectory="C:\Users\Lorenzo\PROGETTI_FPGA"><\/item>
<item  id="604" filename="find_contours/contour_finder.cpp" linenumber="294" name="tmp_91" contextFuncName="contours_finder" moduleName="contours_finder" rtlName="first_hole_center_x_d0" latency="0" BRAM="-1" DSP="-1" FF="-1" LUT="-1" fileDirectory="C:\Users\Lorenzo\PROGETTI_FPGA"><\/item>
<item  id="611" filename="find_contours/contour_finder.cpp" linenumber="301" name="tmp_95" contextFuncName="contours_finder" moduleName="contours_finder" rtlName="tmp_95_fu_2294_p1" latency="0" BRAM="-1" DSP="-1" FF="-1" LUT="-1" fileDirectory="C:\Users\Lorenzo\PROGETTI_FPGA"><\/item>
<item  id="614" filename="find_contours/contour_finder.cpp" linenumber="301" name="tmp_103" contextFuncName="contours_finder" moduleName="contours_finder" rtlName="tmp_103_fu_2299_p4" latency="0" BRAM="-1" DSP="-1" FF="-1" LUT="-1" fileDirectory="C:\Users\Lorenzo\PROGETTI_FPGA"><\/item>
<item  id="615" filename="find_contours/contour_finder.cpp" linenumber="301" name="icmp2" contextFuncName="contours_finder" moduleName="contours_finder" rtlName="icmp2_fu_2309_p2" latency="0" BRAM="-1" DSP="-1" FF="0" LUT="18" fileDirectory="C:\Users\Lorenzo\PROGETTI_FPGA"><\/item>
<item  id="616" filename="find_contours/contour_finder.cpp" linenumber="301" name="not_1" contextFuncName="contours_finder" moduleName="contours_finder" rtlName="not_1_fu_2315_p2" latency="0" BRAM="-1" DSP="-1" FF="0" LUT="11" fileDirectory="C:\Users\Lorenzo\PROGETTI_FPGA"><\/item>
<item  id="617" filename="find_contours/contour_finder.cpp" linenumber="301" name="p_3" contextFuncName="contours_finder" moduleName="contours_finder" rtlName="p_3_fu_2321_p2" latency="0" BRAM="-1" DSP="-1" FF="0" LUT="2" fileDirectory="C:\Users\Lorenzo\PROGETTI_FPGA"><\/item>
<item  id="627" filename="find_contours/contour_finder.cpp" linenumber="308" name="count_closing_3" contextFuncName="contours_finder" moduleName="contours_finder" rtlName="count_closing_3_fu_2326_p2" latency="0" BRAM="-1" DSP="-1" FF="0" LUT="39" fileDirectory="C:\Users\Lorenzo\PROGETTI_FPGA"><\/item>
<item  id="633" filename="find_contours/contour_finder.cpp" linenumber="259" name="count_12" contextFuncName="contours_finder" moduleName="contours_finder" rtlName="count_12_fu_2332_p2" latency="0" BRAM="-1" DSP="-1" FF="0" LUT="39" fileDirectory="C:\Users\Lorenzo\PROGETTI_FPGA"><\/item>
<item  id="639" filename="find_contours/contour_finder.cpp" linenumber="380" name="exitcond" contextFuncName="contours_finder" moduleName="contours_finder" rtlName="exitcond_fu_2338_p2" latency="0" BRAM="-1" DSP="-1" FF="0" LUT="13" fileDirectory="C:\Users\Lorenzo\PROGETTI_FPGA"><\/item>
<item  id="641" filename="find_contours/contour_finder.cpp" linenumber="380" name="count_7" contextFuncName="contours_finder" moduleName="contours_finder" rtlName="count_7_fu_2344_p2" latency="0" BRAM="-1" DSP="-1" FF="0" LUT="14" fileDirectory="C:\Users\Lorenzo\PROGETTI_FPGA"><\/item>
<item  id="644" filename="find_contours/contour_finder.cpp" linenumber="381" name="tmp_65" contextFuncName="contours_finder" moduleName="contours_finder" rtlName="tmp_65_fu_2350_p1" latency="0" BRAM="-1" DSP="-1" FF="-1" LUT="-1" fileDirectory="C:\Users\Lorenzo\PROGETTI_FPGA"><\/item>
<item  id="649" filename="find_contours/contour_finder.cpp" linenumber="386" name="tmp_63" contextFuncName="contours_finder" moduleName="contours_finder" rtlName="tmp_63_fu_2355_p2" latency="0" BRAM="-1" DSP="-1" FF="0" LUT="39" fileDirectory="C:\Users\Lorenzo\PROGETTI_FPGA"><\/item>
<item  id="650" filename="find_contours/contour_finder.cpp" linenumber="387" name="tmp_64" contextFuncName="contours_finder" moduleName="contours_finder" rtlName="tmp_64_fu_2360_p2" latency="0" BRAM="-1" DSP="-1" FF="0" LUT="18" fileDirectory="C:\Users\Lorenzo\PROGETTI_FPGA"><\/item>
<item  id="651" filename="find_contours/contour_finder.cpp" linenumber="387" name="p_1" contextFuncName="contours_finder" moduleName="contours_finder" rtlName="p_1_fu_2366_p3" latency="0" BRAM="-1" DSP="-1" FF="0" LUT="32" fileDirectory="C:\Users\Lorenzo\PROGETTI_FPGA"><\/item>
<item  id="661" filename="find_contours/contour_finder.cpp" linenumber="393" name="tmp_67" contextFuncName="contours_finder" moduleName="contours_finder" rtlName="tmp_67_fu_2380_p2" latency="0" BRAM="-1" DSP="-1" FF="0" LUT="32" fileDirectory="C:\Users\Lorenzo\PROGETTI_FPGA"><\/item>
<item  id="662" filename="find_contours/contour_finder.cpp" linenumber="393" name="tmp_68" contextFuncName="contours_finder" moduleName="contours_finder" rtlName="tmp_68_fu_2386_p2" latency="0" BRAM="-1" DSP="-1" FF="0" LUT="18" fileDirectory="C:\Users\Lorenzo\PROGETTI_FPGA"><\/item>
<item  id="679" filename="find_contours/contour_finder.cpp" linenumber="395" name="count5_cast2" contextFuncName="contours_finder" moduleName="contours_finder" rtlName="count5_cast2_fu_2410_p1" latency="0" BRAM="-1" DSP="-1" FF="-1" LUT="-1" fileDirectory="C:\Users\Lorenzo\PROGETTI_FPGA"><\/item>
<item  id="680" filename="find_contours/contour_finder.cpp" linenumber="395" name="tmp_72" contextFuncName="contours_finder" moduleName="contours_finder" rtlName="tmp_72_fu_2414_p2" latency="0" BRAM="-1" DSP="-1" FF="0" LUT="13" fileDirectory="C:\Users\Lorenzo\PROGETTI_FPGA"><\/item>
<item  id="682" filename="find_contours/contour_finder.cpp" linenumber="395" name="count_8" contextFuncName="contours_finder" moduleName="contours_finder" rtlName="count_8_fu_2420_p2" latency="0" BRAM="-1" DSP="-1" FF="0" LUT="14" fileDirectory="C:\Users\Lorenzo\PROGETTI_FPGA"><\/item>
<item  id="685" filename="find_contours/contour_finder.cpp" linenumber="396" name="tmp_75" contextFuncName="contours_finder" moduleName="contours_finder" rtlName="tmp_75_fu_2426_p1" latency="0" BRAM="-1" DSP="-1" FF="-1" LUT="-1" fileDirectory="C:\Users\Lorenzo\PROGETTI_FPGA"><\/item>
<item  id="688" filename="find_contours/contour_finder.cpp" linenumber="427" name="aValue_last_V_3" contextFuncName="generateAxiValue" moduleName="contours_finder" rtlName="aValue_last_V_3_fu_2431_p2" latency="0" BRAM="-1" DSP="-1" FF="0" LUT="13" fileDirectory="C:\Users\Lorenzo\PROGETTI_FPGA"><\/item>
<item  id="690" filename="find_contours/contour_finder.cpp" linenumber="398" name="tmp_76" contextFuncName="contours_finder" moduleName="contours_finder" rtlName="tmp_76_fu_2437_p1" latency="0" BRAM="-1" DSP="-1" FF="-1" LUT="-1" fileDirectory="C:\Users\Lorenzo\PROGETTI_FPGA"><\/item>
<item  id="693" filename="find_contours/contour_finder.cpp" linenumber="398" name="tmp_77" contextFuncName="contours_finder" moduleName="contours_finder" rtlName="tmp_77_fu_2449_p2" latency="0" BRAM="-1" DSP="-1" FF="0" LUT="39" fileDirectory="C:\Users\Lorenzo\PROGETTI_FPGA"><\/item>
<item  id="697" filename="find_contours/contour_finder.cpp" linenumber="399" name="tmp_78" contextFuncName="contours_finder" moduleName="contours_finder" rtlName="tmp_78_fu_2444_p2" latency="0" BRAM="-1" DSP="-1" FF="0" LUT="39" fileDirectory="C:\Users\Lorenzo\PROGETTI_FPGA"><\/item>
<item  id="701" filename="find_contours/contour_finder.cpp" linenumber="400" name="tmp_79" contextFuncName="contours_finder" moduleName="contours_finder" rtlName="tmp_79_fu_2456_p2" latency="0" BRAM="-1" DSP="-1" FF="0" LUT="39" fileDirectory="C:\Users\Lorenzo\PROGETTI_FPGA"><\/item>
<item  id="708" filename="find_contours/contour_finder.cpp" linenumber="402" name="tmp_80" contextFuncName="contours_finder" moduleName="contours_finder" rtlName="tmp_80_fu_2463_p2" latency="0" BRAM="-1" DSP="-1" FF="0" LUT="13" fileDirectory="C:\Users\Lorenzo\PROGETTI_FPGA"><\/item>
<item  id="710" filename="find_contours/contour_finder.cpp" linenumber="402" name="count_10" contextFuncName="contours_finder" moduleName="contours_finder" rtlName="count_10_fu_2469_p2" latency="0" BRAM="-1" DSP="-1" FF="0" LUT="15" fileDirectory="C:\Users\Lorenzo\PROGETTI_FPGA"><\/item>
<item  id="713" filename="find_contours/contour_finder.cpp" linenumber="403" name="tmp_83" contextFuncName="contours_finder" moduleName="contours_finder" rtlName="tmp_83_fu_2475_p1" latency="0" BRAM="-1" DSP="-1" FF="-1" LUT="-1" fileDirectory="C:\Users\Lorenzo\PROGETTI_FPGA"><\/item>
<item  id="718" filename="find_contours/contour_finder.cpp" linenumber="404" name="tmp_84" contextFuncName="contours_finder" moduleName="contours_finder" rtlName="tmp_84_fu_2480_p2" latency="0" BRAM="-1" DSP="-1" FF="0" LUT="18" fileDirectory="C:\Users\Lorenzo\PROGETTI_FPGA"><\/item>
<item  id="723" filename="find_contours/contour_finder.cpp" linenumber="405" name="tmp_86" contextFuncName="contours_finder" moduleName="contours_finder" rtlName="contours_finder_ulbW_U1" latency="35" BRAM="-1" DSP="-1" FF="-1" LUT="-1" fileDirectory="C:\Users\Lorenzo\PROGETTI_FPGA"><\/item>
<item  id="728" filename="find_contours/contour_finder.cpp" linenumber="406" name="tmp_87" contextFuncName="contours_finder" moduleName="contours_finder" rtlName="contours_finder_ulbW_U2" latency="35" BRAM="-1" DSP="-1" FF="-1" LUT="-1" fileDirectory="C:\Users\Lorenzo\PROGETTI_FPGA"><\/item>
<\/annotationInfo>
</annotationInfo>
